setup.py
snake_case/__init__.py
snake_case/text.py
snake_case.egg-info/PKG-INFO
snake_case.egg-info/SOURCES.txt
snake_case.egg-info/dependency_links.txt
snake_case.egg-info/not-zip-safe
snake_case.egg-info/top_level.txt