Metadata-Version: 1.0
Name: snake-case
Version: 0.0.3
Summary: A systematic approach to parse strings and automate the conversion to snake_case, upperCamelCase or any other case. (Python port of the R snakecase package.)
Home-page: http://github.com/Tazinho/snake_case
Author: Malte Grosser
Author-email: malte.grosser@gmail.com
License: GPL-3
Platform: UNKNOWN
